Workbook

Sheet CartRecovery_DATA
A1: user_id | B1: category_id | C1: last_carted_at
A2: 48282 | B2: 570735 | C2: 43070.366
A3: 189909 | B3: 1464116 | C3: 43069.669
A4: 267270 | B4: 3607361 | C4: 43070.685
A5: 795532 | B5: 154040 | C5: 43070.291
A6: 425978 | B6: 4756105 | C6: 43071.135
A7: 401330 | B7: 3944885 | C7: 43071.246
A8: 880798 | B8: 2355072 | C8: 43072.172
A9: 514845 | B9: 1299190 | C9: 43072.19
A10: 1002755 | B10: 4217906 | C10: 43071.66
A11: 273459 | B11: 4625363 | C11: 43072.002
A12: 223260 | B12: 3004853 | C12: 43072.601
A13: 973755 | B13: 48094 | C13: 43070.424
... A11441: 53669 | B11441: 1673021 | C11441: 43071.068

Sheet CartRecovery_Assumptions
A1: Assumed Cart Value | B1: Recovery Rate – Low | C1: Recovery Rate – Mid | D1: Recovery Rate – High | E1: Total Abandoned Carts | F1: SMS Cost per User
A2: 500 | B2: 0.2 | C2: 0.25 | D2: 0.3 | E2: 11440 | F2: 1

Sheet CartRecovery_Simulated_Solution
A1: Projected Solution | B1: Carts Recovered | C1: Revenue Generated | D1: Campaign Cost | E1: Net Recovery | F1: Abandoned Carts
A2: Projected Revenue – Low | B2: =Table9[[#This Row],[Total Abandoned Carts]]*Table9[[#This Row],[Recovery Rate – Low]] -> 2288 | C2: =Table11[[#This Row],[Carts Recovered]]*500 -> 1144000 | D2: =Table9[[#This Row],[Total Abandoned Carts]]*1 -> 11440 | E2: =C2-D2 -> 1132560 | F2: =Table11[[#This Row],[Campaign Cost]] -> 11440
A3: Projected Revenue – Mid | B3: {=Table9[Total Abandoned Carts]*Table9[Recovery Rate – Mid]} -> 2860 | C3: =Table11[[#This Row],[Carts Recovered]]*500 -> 1430000 | D3: 11440 | E3: =C3-D3 -> 1418560 | F3: =Table11[[#This Row],[Campaign Cost]] -> 11440
A4: Projected Revenue – High | B4: {=Table9[Recovery Rate – High]*Table9[Total Abandoned Carts]} -> 3432 | C4: =Table11[[#This Row],[Carts Recovered]]*500 -> 1716000 | D4: {=Table9[Total Abandoned Carts]*Table9[SMS Cost per User]} -> 11440 | E4: =C4-D4 -> 1704560 | F4: =Table11[[#This Row],[Campaign Cost]] -> 11440

Sheet Sheet1
A1: category_id | B1: total_actions | C1: total_views | D1: total_favorites | E1: total_carted | F1: total_converted | G1: Conversion Rate
A2: 2355072 | B2: 17114 | C2: 15947 | D2: 478 | E2: 646 | F2: 46 | G2: =F2/C2 -> 0.0028845551
A3: 2520377 | B3: 11555 | C3: 10676 | D3: 383 | E3: 460 | F3: 38 | G3: =F3/C3 -> 0.0035593855
A4: 1080785 | B4: 5335 | C4: 4945 | D4: 193 | E4: 188 | F4: 11 | G4: =F4/C4 -> 0.0022244692
A5: 4181361 | B5: 5325 | C5: 4800 | D5: 206 | E5: 286 | F5: 38 | G5: =F5/C5 -> 0.0079166667
A6: 154040 | B6: 4679 | C6: 4431 | D6: 110 | E6: 131 | F6: 7 | G6: =F6/C6 -> 0.0015797788
A7: 2920476 | B7: 3650 | C7: 3382 | D7: 109 | E7: 148 | F7: 11 | G7: =F7/C7 -> 0.0032525133
A8: 4170419 | B8: 3145 | C8: 2923 | D8: 75 | E8: 126 | F8: 22 | G8: =F8/C8 -> 0.0075265139
A9: 2939262 | B9: 2974 | C9: 2715 | D9: 69 | E9: 155 | F9: 37 | G9: =F9/C9 -> 0.013627993
A10: 4643350 | B10: 2877 | C10: 2627 | D10: 86 | E10: 139 | F10: 26 | G10: =F10/C10 -> 0.0098972212

Sheet HighPotentialSKUs-Data
A1: category_id | B1: total_actions | C1: total_views | D1: total_favorites | E1: total_carted | F1: total_converted | G1: conversion rate
A2: 2355072 | B2: 17114 | C2: 15947 | D2: 478 | E2: 646 | F2: 46 | G2: =High_Potential_SKUs[[#This Row],[total_converted]]/High_Potential_SKUs[[#This Row],[total_views]] -> 0.0028845551
A3: 2520377 | B3: 11555 | C3: 10676 | D3: 383 | E3: 460 | F3: 38 | G3: =High_Potential_SKUs[[#This Row],[total_converted]]/High_Potential_SKUs[[#This Row],[total_views]] -> 0.0035593855
A4: 1080785 | B4: 5335 | C4: 4945 | D4: 193 | E4: 188 | F4: 11 | G4: =High_Potential_SKUs[[#This Row],[total_converted]]/High_Potential_SKUs[[#This Row],[total_views]] -> 0.0022244692
A5: 4181361 | B5: 5325 | C5: 4800 | D5: 206 | E5: 286 | F5: 38 | G5: =High_Potential_SKUs[[#This Row],[total_converted]]/High_Potential_SKUs[[#This Row],[total_views]] -> 0.0079166667
A6: 154040 | B6: 4679 | C6: 4431 | D6: 110 | E6: 131 | F6: 7 | G6: =High_Potential_SKUs[[#This Row],[total_converted]]/High_Potential_SKUs[[#This Row],[total_views]] -> 0.0015797788
A7: 2920476 | B7: 3650 | C7: 3382 | D7: 109 | E7: 148 | F7: 11 | G7: =High_Potential_SKUs[[#This Row],[total_converted]]/High_Potential_SKUs[[#This Row],[total_views]] -> 0.0032525133
A8: 4170419 | B8: 3145 | C8: 2923 | D8: 75 | E8: 126 | F8: 22 | G8: =High_Potential_SKUs[[#This Row],[total_converted]]/High_Potential_SKUs[[#This Row],[total_views]] -> 0.0075265139
A9: 2939262 | B9: 2974 | C9: 2715 | D9: 69 | E9: 155 | F9: 37 | G9: =High_Potential_SKUs[[#This Row],[total_converted]]/High_Potential_SKUs[[#This Row],[total_views]] -> 0.013627993
A10: 4643350 | B10: 2877 | C10: 2627 | D10: 86 | E10: 139 | F10: 26 | G10: =High_Potential_SKUs[[#This Row],[total_converted]]/High_Potential_SKUs[[#This Row],[total_views]] -> 0.0098972212
A11: 1029459 | B11: 2720 | C11: 2448 | D11: 88 | E11: 138 | F11: 49 | G11: =High_Potential_SKUs[[#This Row],[total_converted]]/High_Potential_SKUs[[#This Row],[total_views]] -> 0.02001634
A12: 1859277 | B12: 2599 | C12: 2396 | D12: 61 | E12: 132 | F12: 11 | G12: =High_Potential_SKUs[[#This Row],[total_converted]]/High_Potential_SKUs[[#This Row],[total_views]] -> 0.004590985
A13: 2096639 | B13: 2229 | C13: 2135 | D13: 18 | E13: 58 | F13: 20 | G13: =High_Potential_SKUs[[#This Row],[total_converted]]/High_Potential_SKUs[[#This Row],[total_views]] -> 0.0093676815
... A25: 2558244 | B25: 1662 | C25: 1508 | D25: 37 | E25: 99 | F25: 19 | G25: =High_Potential_SKUs[[#This Row],[total_converted]]/High_Potential_SKUs[[#This Row],[total_views]] -> 0.012599469

Sheet HighPotentialSKUs-Assumptions
A1: Total High-Attention Categories | B1: Avg Views per Category | C1: Monetization Target (%) | D1: Avg Conversion Rate (Base) | E1: SKUs Targeted | F1: Total Views (Top SKUs) | G1: Avg SKU Price | H1: Lifted Conversion Rate
A2: =COUNTA('HighPotentialSKUs-Data'!A2:A25) -> 24 | B2: =AVERAGE('HighPotentialSKUs-Data'!C2:'HighPotentialSKUs-Data'!C25) -> 3359.2917 | C2: 0.2 | D2: =SUM('HighPotentialSKUs-Data'!F2:'HighPotentialSKUs-Data'!F25)/SUM('HighPotentialSKUs-Data'!C2:'HighPotentialSKUs-Data'!C25) -> 0.0073428178 | E2: =ROUND(Table14[[#This Row],[Total High-Attention Categories]] * C2, 0) -> 5 | F2: {=SUM(LARGE('HighPotentialSKUs-Data'!C2:C25, {1,2,3,4,5}))} -> 40799 | G2: 600 | H2: 0.03

Sheet HighPotentialSKUs-Simulated_Sol
A1: Projected Solution | B1: SKUs Targeted | C1: Views | D1: Projected Conversions | E1: Revenue Generated | F1: Conversion Rate | G1: Revenue Per SKU | H1: Revenue Per View | I1: Conversion Uplift vs Base | J1: Revenue Uplift vs Base | K1: Label for Waterfall | L1: Waterfall Value | M1: Waterfall Type
A2: Base Scenario | B2: =Table14[[#This Row],[SKUs Targeted]] -> 5 | C2: =Table14[[#This Row],[Total Views (Top SKUs)]] -> 40799 | D2: {=SUM(LARGE('HighPotentialSKUs-Data'!F2:F25,{1,2,3,4,5}))} -> 211 | E2: =D2*600 -> 126600 | F2: =Table13[[#This Row],[Projected Conversions]]/Table13[[#This Row],[Views]] -> 0.0051716954 | G2: =Table13[[#This Row],[Revenue Generated]]/Table13[[#This Row],[SKUs Targeted]] -> 25320 | H2: =ROUND(Table13[[#This Row],[Revenue Generated]]/Table13[[#This Row],[Views]],2) -> 3.1 | I2: - | J2: - | K2: Base Revenue | L2: 126600 | M2: Start
A3: Optimized Scenario | B3: {=Table14[SKUs Targeted]} -> 5 | C3: {=Table14[Total Views (Top SKUs)]} -> 40799 | D3: {=ROUND(Table14[Total Views (Top SKUs)]*Table14[Lifted Conversion Rate],0)} -> 1224 | E3: =D3*600 -> 734400 | F3: =ROUND(Table13[[#This Row],[Projected Conversions]]/Table13[[#This Row],[Views]],4) -> 0.03 | G3: =Table13[[#This Row],[Revenue Generated]]/Table13[[#This Row],[SKUs Targeted]] -> 146880 | H3: =ROUND(Table13[[#This Row],[Revenue Generated]]/Table13[[#This Row],[Views]],2) -> 18 | I3: =Table13[[#This Row],[Conversion Rate]]-F2 -> 0.024828305 | J3: =Table13[[#This Row],[Revenue Generated]]-E2 -> 607800 | K3: Revenue from Lift | L3: 607800 | M3: Increase
K4: Final Revenue | L4: 734400 | M4: Total

Sheet CohortRetention-Data
A1: cohort_week | B1: cohort_week_number | C1: users | D1: total_sessions | E1: avg_sessions_per_user | F1: users_2plus_sessions | G1: session_1_to_2_retention
A2: 43064 | B2: 47 | C2: 33670 | D2: 36085 | E2: 1.07 | F2: 2216 | G2: 6.58
A3: 43065 | B3: 48 | C3: 33497 | D3: 35723 | E3: 1.07 | F3: 2069 | G3: 6.18
A4: 43066 | B4: 48 | C4: 30540 | D4: 32441 | E4: 1.06 | F4: 1749 | G4: 5.73
A5: 43067 | B5: 48 | C5: 29844 | D5: 31704 | E5: 1.06 | F5: 1713 | G5: 5.74
A6: 43068 | B6: 48 | C6: 32270 | D6: 34229 | E6: 1.06 | F6: 1818 | G6: 5.63
A7: 43069 | B7: 48 | C7: 33365 | D7: 35595 | E7: 1.07 | F7: 2054 | G7: 6.16
A8: 43070 | B8: 48 | C8: 37198 | D8: 39779 | E8: 1.07 | F8: 2380 | G8: 6.4
A9: 43071 | B9: 48 | C9: 51586 | D9: 55608 | E9: 1.08 | F9: 3684 | G9: 7.14
A10: 43072 | B10: 49 | C10: 43536 | D10: 46353 | E10: 1.06 | F10: 2588 | G10: 5.94

Sheet CohortRetention-Assumptions
A1: Scenario | B1: Target Retention % | C1: Avg Revenue gain per user
A2: Conservative Improvement | B2: 0.15 | C2: 250
A3: Industry Benchmark | B3: 0.25 | C3: 250
A4: Best-Case Scenario | B4: 0.3 | C4: 250

Sheet CohortRetention-Simulated_sol
A1: cohort_week | B1: users | C1: current_retention | D1: Current_Users_Retained
A2: 43064 | B2: 33670 | C2: 6.58 | D2: =ROUND(B2*C2/100,0) -> 2215
A3: 43065 | B3: 33497 | C3: 6.18 | D3: =ROUND(B3*C3/100,0) -> 2070
A4: 43066 | B4: 30540 | C4: 5.73 | D4: =ROUND(B4*C4/100,0) -> 1750
A5: 43067 | B5: 29844 | C5: 5.74 | D5: =ROUND(B5*C5/100,0) -> 1713
A6: 43068 | B6: 32270 | C6: 5.63 | D6: =ROUND(B6*C6/100,0) -> 1817
A7: 43069 | B7: 33365 | C7: 6.16 | D7: =ROUND(B7*C7/100,0) -> 2055
A8: 43070 | B8: 37198 | C8: 6.4 | D8: =ROUND(B8*C8/100,0) -> 2381
A9: 43071 | B9: 51586 | C9: 7.14 | D9: =ROUND(B9*C9/100,0) -> 3683
A10: 43072 | B10: 43536 | C10: 5.94 | D10: =ROUND(B10*C10/100,0) -> 2586
A12: Scenario 1 - Conservative Improvement | E12: Scenario 2 - Industry Benchmark
A15: users_retained_Conservative_Improvement | B15: Additional_users_retained | C15: Revenue Gain_CI | E15: users_retained_Benchmark | F15: Additional_users_retained | G15: Revenue Gain_benchmark
A16: =ROUND(B2*15/100,0) -> 5051 | B16: =ROUND(A16-D2,0) -> 2836 | C16: =B16*250 -> 709000 | E16: =ROUND(B2*25/100,0) -> 8418 | F16: =E16-D2 -> 6203 | G16: =F16*250 -> 1550750
A17: =ROUND(B3*15/100,0) -> 5025 | B17: =ROUND(A17-D3,0) -> 2955 | C17: =B17*250 -> 738750 | E17: =ROUND(B3*25/100,0) -> 8374 | F17: =E17-D3 -> 6304 | G17: =F17*250 -> 1576000
A18: =ROUND(B4*15/100,0) -> 4581 | B18: =ROUND(A18-D4,0) -> 2831 | C18: =B18*250 -> 707750 | E18: =ROUND(B4*25/100,0) -> 7635 | F18: =E18-D4 -> 5885 | G18: =F18*250 -> 1471250
A19: =ROUND(B5*15/100,0) -> 4477 | B19: =ROUND(A19-D5,0) -> 2764 | C19: =B19*250 -> 691000 | E19: =ROUND(B5*25/100,0) -> 7461 | F19: =E19-D5 -> 5748 | G19: =F19*250 -> 1437000
A20: =ROUND(B6*15/100,0) -> 4841 | B20: =ROUND(A20-D6,0) -> 3024 | C20: =B20*250 -> 756000 | E20: =ROUND(B6*25/100,0) -> 8068 | F20: =E20-D6 -> 6251 | G20: =F20*250 -> 1562750
A21: =ROUND(B7*15/100,0) -> 5005 | B21: =ROUND(A21-D7,0) -> 2950 | C21: =B21*250 -> 737500 | E21: =ROUND(B7*25/100,0) -> 8341 | F21: =E21-D7 -> 6286 | G21: =F21*250 -> 1571500
A22: =ROUND(B8*15/100,0) -> 5580 | B22: =ROUND(A22-D8,0) -> 3199 | C22: =B22*250 -> 799750 | E22: =ROUND(B8*25/100,0) -> 9300 | F22: =E22-D8 -> 6919 | G22: =F22*250 -> 1729750
A23: =ROUND(B9*15/100,0) -> 7738 | B23: =ROUND(A23-D9,0) -> 4055 | C23: =B23*250 -> 1013750 | E23: =ROUND(B9*25/100,0) -> 12897 | F23: =E23-D9 -> 9214 | G23: =F23*250 -> 2303500
A24: =ROUND(B10*15/100,0) -> 6530 | B24: =ROUND(A24-D10,0) -> 3944 | C24: =B24*250 -> 986000 | E24: =ROUND(B10*25/100,0) -> 10884 | F24: =E24-D10 -> 8298 | G24: =F24*250 -> 2074500
A27: Scenario 3 - Best_Case Scenario
A30: users_retained_Best_case | B30: Additional_users_retained | C30: Revenue Gain_BestCase
A31: =ROUND(B2*30/100,0) -> 10101 | B31: =A31-D2 -> 7886 | C31: =B31*250 -> 1971500
A32: =ROUND(B3*30/100,0) -> 10049 | B32: =A32-D3 -> 7979 | C32: =B32*250 -> 1994750
A33: =ROUND(B4*30/100,0) -> 9162 | B33: =A33-D4 -> 7412 | C33: =B33*250 -> 1853000
A34: =ROUND(B5*30/100,0) -> 8953 | B34: =A34-D5 -> 7240 | C34: =B34*250 -> 1810000
A35: =ROUND(B6*30/100,0) -> 9681 | B35: =A35-D6 -> 7864 | C35: =B35*250 -> 1966000
A36: =ROUND(B7*30/100,0) -> 10010 | B36: =A36-D7 -> 7955 | C36: =B36*250 -> 1988750
A37: =ROUND(B8*30/100,0) -> 11159 | B37: =A37-D8 -> 8778 | C37: =B37*250 -> 2194500
A38: =ROUND(B9*30/100,0) -> 15476 | B38: =A38-D9 -> 11793 | C38: =B38*250 -> 2948250
A39: =ROUND(B10*30/100,0) -> 13061 | B39: =A39-D10 -> 10475 | C39: =B39*250 -> 2618750

Sheet CohortRetention-Final
A1: cohort_week | B1: users | C1: current_retention | D1: current_retention2 | E1: Current_Users_Retained | F1: Estimated Revenue | G1: users_retained_Conservative_Improvement | H1: users_retained_Benchmark | I1: users_retained_Best_case | J1: Additional_users_Conservative | K1: Additional_users_Benchmark | L1: Additional_users_BestCase | M1: Revenue Gain_CI | N1: Revenue Gain_benchmark | O1: Revenue Gain_BestCase
A2: 43064 | B2: 33670 | C2: =D2/100 -> 0.0658 | D2: 6.58 | E2: =ROUND(B2*D2/100,0) -> 2215 | F2: =Table117[[#This Row],[Current_Users_Retained]]*250 -> 553750 | G2: 5051 | H2: 8418 | I2: 10101 | J2: ='CohortRetention-Simulated_sol'!B16 -> 2836 | K2: ='CohortRetention-Simulated_sol'!F16 -> 6203 | L2: ='CohortRetention-Simulated_sol'!B31 -> 7886 | M2: ='CohortRetention-Simulated_sol'!C16 -> 709000 | N2: ='CohortRetention-Simulated_sol'!G16 -> 1550750 | O2: ='CohortRetention-Simulated_sol'!C31 -> 1971500
A3: 43065 | B3: 33497 | C3: =D3/100 -> 0.0618 | D3: 6.18 | E3: =ROUND(B3*D3/100,0) -> 2070 | F3: =Table117[[#This Row],[Current_Users_Retained]]*250 -> 517500 | G3: 5025 | H3: 8374 | I3: 10049 | J3: ='CohortRetention-Simulated_sol'!B17 -> 2955 | K3: ='CohortRetention-Simulated_sol'!F17 -> 6304 | L3: ='CohortRetention-Simulated_sol'!B32 -> 7979 | M3: ='CohortRetention-Simulated_sol'!C17 -> 738750 | N3: ='CohortRetention-Simulated_sol'!G17 -> 1576000 | O3: ='CohortRetention-Simulated_sol'!C32 -> 1994750
A4: 43066 | B4: 30540 | C4: =D4/100 -> 0.0573 | D4: 5.73 | E4: =ROUND(B4*D4/100,0) -> 1750 | F4: =Table117[[#This Row],[Current_Users_Retained]]*250 -> 437500 | G4: 4581 | H4: 7635 | I4: 9162 | J4: ='CohortRetention-Simulated_sol'!B18 -> 2831 | K4: ='CohortRetention-Simulated_sol'!F18 -> 5885 | L4: ='CohortRetention-Simulated_sol'!B33 -> 7412 | M4: ='CohortRetention-Simulated_sol'!C18 -> 707750 | N4: ='CohortRetention-Simulated_sol'!G18 -> 1471250 | O4: ='CohortRetention-Simulated_sol'!C33 -> 1853000
A5: 43067 | B5: 29844 | C5: =D5/100 -> 0.0574 | D5: 5.74 | E5: =ROUND(B5*D5/100,0) -> 1713 | F5: =Table117[[#This Row],[Current_Users_Retained]]*250 -> 428250 | G5: 4477 | H5: 7461 | I5: 8953 | J5: ='CohortRetention-Simulated_sol'!B19 -> 2764 | K5: ='CohortRetention-Simulated_sol'!F19 -> 5748 | L5: ='CohortRetention-Simulated_sol'!B34 -> 7240 | M5: ='CohortRetention-Simulated_sol'!C19 -> 691000 | N5: ='CohortRetention-Simulated_sol'!G19 -> 1437000 | O5: ='CohortRetention-Simulated_sol'!C34 -> 1810000
A6: 43068 | B6: 32270 | C6: =D6/100 -> 0.0563 | D6: 5.63 | E6: =ROUND(B6*D6/100,0) -> 1817 | F6: =Table117[[#This Row],[Current_Users_Retained]]*250 -> 454250 | G6: 4841 | H6: 8068 | I6: 9681 | J6: ='CohortRetention-Simulated_sol'!B20 -> 3024 | K6: ='CohortRetention-Simulated_sol'!F20 -> 6251 | L6: ='CohortRetention-Simulated_sol'!B35 -> 7864 | M6: ='CohortRetention-Simulated_sol'!C20 -> 756000 | N6: ='CohortRetention-Simulated_sol'!G20 -> 1562750 | O6: ='CohortRetention-Simulated_sol'!C35 -> 1966000
A7: 43069 | B7: 33365 | C7: =D7/100 -> 0.0616 | D7: 6.16 | E7: =ROUND(B7*D7/100,0) -> 2055 | F7: =Table117[[#This Row],[Current_Users_Retained]]*250 -> 513750 | G7: 5005 | H7: 8341 | I7: 10010 | J7: ='CohortRetention-Simulated_sol'!B21 -> 2950 | K7: ='CohortRetention-Simulated_sol'!F21 -> 6286 | L7: ='CohortRetention-Simulated_sol'!B36 -> 7955 | M7: ='CohortRetention-Simulated_sol'!C21 -> 737500 | N7: ='CohortRetention-Simulated_sol'!G21 -> 1571500 | O7: ='CohortRetention-Simulated_sol'!C36 -> 1988750
A8: 43070 | B8: 37198 | C8: =D8/100 -> 0.064 | D8: 6.4 | E8: =ROUND(B8*D8/100,0) -> 2381 | F8: =Table117[[#This Row],[Current_Users_Retained]]*250 -> 595250 | G8: 5580 | H8: 9300 | I8: 11159 | J8: ='CohortRetention-Simulated_sol'!B22 -> 3199 | K8: ='CohortRetention-Simulated_sol'!F22 -> 6919 | L8: ='CohortRetention-Simulated_sol'!B37 -> 8778 | M8: ='CohortRetention-Simulated_sol'!C22 -> 799750 | N8: ='CohortRetention-Simulated_sol'!G22 -> 1729750 | O8: ='CohortRetention-Simulated_sol'!C37 -> 2194500
A9: 43071 | B9: 51586 | C9: =D9/100 -> 0.0714 | D9: 7.14 | E9: =ROUND(B9*D9/100,0) -> 3683 | F9: =Table117[[#This Row],[Current_Users_Retained]]*250 -> 920750 | G9: 7738 | H9: 12897 | I9: 15476 | J9: ='CohortRetention-Simulated_sol'!B23 -> 4055 | K9: ='CohortRetention-Simulated_sol'!F23 -> 9214 | L9: ='CohortRetention-Simulated_sol'!B38 -> 11793 | M9: ='CohortRetention-Simulated_sol'!C23 -> 1013750 | N9: ='CohortRetention-Simulated_sol'!G23 -> 2303500 | O9: ='CohortRetention-Simulated_sol'!C38 -> 2948250
A10: 43072 | B10: 43536 | C10: =D10/100 -> 0.0594 | D10: 5.94 | E10: =ROUND(B10*D10/100,0) -> 2586 | F10: =Table117[[#This Row],[Current_Users_Retained]]*250 -> 646500 | G10: 6530 | H10: 10884 | I10: 13061 | J10: ='CohortRetention-Simulated_sol'!B24 -> 3944 | K10: ='CohortRetention-Simulated_sol'!F24 -> 8298 | L10: ='CohortRetention-Simulated_sol'!B39 -> 10475 | M10: ='CohortRetention-Simulated_sol'!C24 -> 986000 | N10: ='CohortRetention-Simulated_sol'!G24 -> 2074500 | O10: ='CohortRetention-Simulated_sol'!C39 -> 2618750

Sheet HighLatencyPairs-Data
A1: user_id | B1: product_id | C1: avg_time_to_convert
A2: 44814 | B2: 48995 | C2: 5041.3333
A3: 236463 | B3: 60692 | C3: 5033.2
A4: 73876 | B4: 317032 | C4: 4312
A5: 963253 | B5: 344968 | C5: 4092.3333
A6: 179022 | B6: 891289 | C6: 11246.467
A7: 449416 | B7: 1109510 | C7: 3755.5833
A8: 148991 | B8: 1178516 | C8: 4764.1667
A9: 968220 | B9: 1208487 | C9: 11275.483
A10: 172074 | B10: 1838487 | C10: 4752.6
A11: 752173 | B11: 1893188 | C11: 6049.2833
A12: 925984 | B12: 1938055 | C12: 4104.1
A13: 454977 | B13: 1999347 | C13: 5783.4833
... A348: 892241 | B348: 5134469 | C348: 4751.5333

Sheet HighLatencyPairs-Simulated Sol
A1: user_id | B1: product_id | C1: avg_time_to_convert in Minutes | D1: Latency Segment | E1: Campaign ROI | F1: Average time to convert in Days | G1: Improved Time to convert | H1: Time Saved | I1: % Conversion Speedup
A2: 44814 | B2: 48995 | C2: 5041.3333 | D2: =IF(F2<=2.5, "Low", IF(F2<=3.5, "Medium", IF(F2<=5.5, "High", "Very High"))) -> Medium | E2: =IF(D2="Very High", 300, IF(D2="High", 200, IF(D2="Medium", 100, 50))) -> 100 | F2: =ROUND(C2/1440,2) -> 3.5 | G2: =IF(D2="High", F2*0.7, IF(D2="Very High", F2*0.65, F2)) -> 3.5 | H2: =ROUND(Latency_Based_Targeting18[[#This Row],[Average time to convert in Days]]-Latency_Based_Targeting18[[#This Row],[Improved Time to convert]],2) -> 0 | I2: =Latency_Based_Targeting18[[#This Row],[Time Saved]]/Latency_Based_Targeting18[[#This Row],[Average time to convert in Days]] -> 0
A3: 236463 | B3: 60692 | C3: 5033.2 | D3: =IF(F3<=2.5, "Low", IF(F3<=3.5, "Medium", IF(F3<=5.5, "High", "Very High"))) -> Medium | E3: =IF(D3="Very High", 300, IF(D3="High", 200, IF(D3="Medium", 100, 50))) -> 100 | F3: =ROUND(C3/1440,2) -> 3.5 | G3: =IF(D3="High", F3*0.7, IF(D3="Very High", F3*0.65, F3)) -> 3.5 | H3: =ROUND(Latency_Based_Targeting18[[#This Row],[Average time to convert in Days]]-Latency_Based_Targeting18[[#This Row],[Improved Time to convert]],2) -> 0 | I3: =Latency_Based_Targeting18[[#This Row],[Time Saved]]/Latency_Based_Targeting18[[#This Row],[Average time to convert in Days]] -> 0
A4: 73876 | B4: 317032 | C4: 4312 | D4: =IF(F4<=2.5, "Low", IF(F4<=3.5, "Medium", IF(F4<=5.5, "High", "Very High"))) -> Medium | E4: =IF(D4="Very High", 300, IF(D4="High", 200, IF(D4="Medium", 100, 50))) -> 100 | F4: =ROUND(C4/1440,2) -> 2.99 | G4: =IF(D4="High", F4*0.7, IF(D4="Very High", F4*0.65, F4)) -> 2.99 | H4: =ROUND(Latency_Based_Targeting18[[#This Row],[Average time to convert in Days]]-Latency_Based_Targeting18[[#This Row],[Improved Time to convert]],2) -> 0 | I4: =Latency_Based_Targeting18[[#This Row],[Time Saved]]/Latency_Based_Targeting18[[#This Row],[Average time to convert in Days]] -> 0
A5: 963253 | B5: 344968 | C5: 4092.3333 | D5: =IF(F5<=2.5, "Low", IF(F5<=3.5, "Medium", IF(F5<=5.5, "High", "Very High"))) -> Medium | E5: =IF(D5="Very High", 300, IF(D5="High", 200, IF(D5="Medium", 100, 50))) -> 100 | F5: =ROUND(C5/1440,2) -> 2.84 | G5: =IF(D5="High", F5*0.7, IF(D5="Very High", F5*0.65, F5)) -> 2.84 | H5: =ROUND(Latency_Based_Targeting18[[#This Row],[Average time to convert in Days]]-Latency_Based_Targeting18[[#This Row],[Improved Time to convert]],2) -> 0 | I5: =Latency_Based_Targeting18[[#This Row],[Time Saved]]/Latency_Based_Targeting18[[#This Row],[Average time to convert in Days]] -> 0
A6: 179022 | B6: 891289 | C6: 11246.467 | D6: =IF(F6<=2.5, "Low", IF(F6<=3.5, "Medium", IF(F6<=5.5, "High", "Very High"))) -> Very High | E6: =IF(D6="Very High", 300, IF(D6="High", 200, IF(D6="Medium", 100, 50))) -> 300 | F6: =ROUND(C6/1440,2) -> 7.81 | G6: =IF(D6="High", F6*0.7, IF(D6="Very High", F6*0.65, F6)) -> 5.0765 | H6: =ROUND(Latency_Based_Targeting18[[#This Row],[Average time to convert in Days]]-Latency_Based_Targeting18[[#This Row],[Improved Time to convert]],2) -> 2.73 | I6: =Latency_Based_Targeting18[[#This Row],[Time Saved]]/Latency_Based_Targeting18[[#This Row],[Average time to convert in Days]] -> 0.34955186
A7: 449416 | B7: 1109510 | C7: 3755.5833 | D7: =IF(F7<=2.5, "Low", IF(F7<=3.5, "Medium", IF(F7<=5.5, "High", "Very High"))) -> Medium | E7: =IF(D7="Very High", 300, IF(D7="High", 200, IF(D7="Medium", 100, 50))) -> 100 | F7: =ROUND(C7/1440,2) -> 2.61 | G7: =IF(D7="High", F7*0.7, IF(D7="Very High", F7*0.65, F7)) -> 2.61 | H7: =ROUND(Latency_Based_Targeting18[[#This Row],[Average time to convert in Days]]-Latency_Based_Targeting18[[#This Row],[Improved Time to convert]],2) -> 0 | I7: =Latency_Based_Targeting18[[#This Row],[Time Saved]]/Latency_Based_Targeting18[[#This Row],[Average time to convert in Days]] -> 0
A8: 148991 | B8: 1178516 | C8: 4764.1667 | D8: =IF(F8<=2.5, "Low", IF(F8<=3.5, "Medium", IF(F8<=5.5, "High", "Very High"))) -> Medium | E8: =IF(D8="Very High", 300, IF(D8="High", 200, IF(D8="Medium", 100, 50))) -> 100 | F8: =ROUND(C8/1440,2) -> 3.31 | G8: =IF(D8="High", F8*0.7, IF(D8="Very High", F8*0.65, F8)) -> 3.31 | H8: =ROUND(Latency_Based_Targeting18[[#This Row],[Average time to convert in Days]]-Latency_Based_Targeting18[[#This Row],[Improved Time to convert]],2) -> 0 | I8: =Latency_Based_Targeting18[[#This Row],[Time Saved]]/Latency_Based_Targeting18[[#This Row],[Average time to convert in Days]] -> 0
A9: 968220 | B9: 1208487 | C9: 11275.483 | D9: =IF(F9<=2.5, "Low", IF(F9<=3.5, "Medium", IF(F9<=5.5, "High", "Very High"))) -> Very High | E9: =IF(D9="Very High", 300, IF(D9="High", 200, IF(D9="Medium", 100, 50))) -> 300 | F9: =ROUND(C9/1440,2) -> 7.83 | G9: =IF(D9="High", F9*0.7, IF(D9="Very High", F9*0.65, F9)) -> 5.0895 | H9: =ROUND(Latency_Based_Targeting18[[#This Row],[Average time to convert in Days]]-Latency_Based_Targeting18[[#This Row],[Improved Time to convert]],2) -> 2.74 | I9: =Latency_Based_Targeting18[[#This Row],[Time Saved]]/Latency_Based_Targeting18[[#This Row],[Average time to convert in Days]] -> 0.34993614
A10: 172074 | B10: 1838487 | C10: 4752.6 | D10: =IF(F10<=2.5, "Low", IF(F10<=3.5, "Medium", IF(F10<=5.5, "High", "Very High"))) -> Medium | E10: =IF(D10="Very High", 300, IF(D10="High", 200, IF(D10="Medium", 100, 50))) -> 100 | F10: =ROUND(C10/1440,2) -> 3.3 | G10: =IF(D10="High", F10*0.7, IF(D10="Very High", F10*0.65, F10)) -> 3.3 | H10: =ROUND(Latency_Based_Targeting18[[#This Row],[Average time to convert in Days]]-Latency_Based_Targeting18[[#This Row],[Improved Time to convert]],2) -> 0 | I10: =Latency_Based_Targeting18[[#This Row],[Time Saved]]/Latency_Based_Targeting18[[#This Row],[Average time to convert in Days]] -> 0
A11: 752173 | B11: 1893188 | C11: 6049.2833 | D11: =IF(F11<=2.5, "Low", IF(F11<=3.5, "Medium", IF(F11<=5.5, "High", "Very High"))) -> High | E11: =IF(D11="Very High", 300, IF(D11="High", 200, IF(D11="Medium", 100, 50))) -> 200 | F11: =ROUND(C11/1440,2) -> 4.2 | G11: =IF(D11="High", F11*0.7, IF(D11="Very High", F11*0.65, F11)) -> 2.94 | H11: =ROUND(Latency_Based_Targeting18[[#This Row],[Average time to convert in Days]]-Latency_Based_Targeting18[[#This Row],[Improved Time to convert]],2) -> 1.26 | I11: =Latency_Based_Targeting18[[#This Row],[Time Saved]]/Latency_Based_Targeting18[[#This Row],[Average time to convert in Days]] -> 0.3
A12: 925984 | B12: 1938055 | C12: 4104.1 | D12: =IF(F12<=2.5, "Low", IF(F12<=3.5, "Medium", IF(F12<=5.5, "High", "Very High"))) -> Medium | E12: =IF(D12="Very High", 300, IF(D12="High", 200, IF(D12="Medium", 100, 50))) -> 100 | F12: =ROUND(C12/1440,2) -> 2.85 | G12: =IF(D12="High", F12*0.7, IF(D12="Very High", F12*0.65, F12)) -> 2.85 | H12: =ROUND(Latency_Based_Targeting18[[#This Row],[Average time to convert in Days]]-Latency_Based_Targeting18[[#This Row],[Improved Time to convert]],2) -> 0 | I12: =Latency_Based_Targeting18[[#This Row],[Time Saved]]/Latency_Based_Targeting18[[#This Row],[Average time to convert in Days]] -> 0
A13: 454977 | B13: 1999347 | C13: 5783.4833 | D13: =IF(F13<=2.5, "Low", IF(F13<=3.5, "Medium", IF(F13<=5.5, "High", "Very High"))) -> High | E13: =IF(D13="Very High", 300, IF(D13="High", 200, IF(D13="Medium", 100, 50))) -> 200 | F13: =ROUND(C13/1440,2) -> 4.02 | G13: =IF(D13="High", F13*0.7, IF(D13="Very High", F13*0.65, F13)) -> 2.814 | H13: =ROUND(Latency_Based_Targeting18[[#This Row],[Average time to convert in Days]]-Latency_Based_Targeting18[[#This Row],[Improved Time to convert]],2) -> 1.21 | I13: =Latency_Based_Targeting18[[#This Row],[Time Saved]]/Latency_Based_Targeting18[[#This Row],[Average time to convert in Days]] -> 0.30099502
... A348: 892241 | B348: 5134469 | C348: 4751.5333 | D348: =IF(F348<=2.5, "Low", IF(F348<=3.5, "Medium", IF(F348<=5.5, "High", "Very High"))) -> Medium | E348: =IF(D348="Very High", 300, IF(D348="High", 200, IF(D348="Medium", 100, 50))) -> 100 | F348: =ROUND(C348/1440,2) -> 3.3 | G348: =IF(D348="High", F348*0.7, IF(D348="Very High", F348*0.65, F348)) -> 3.3 | H348: =ROUND(Latency_Based_Targeting18[[#This Row],[Average time to convert in Days]]-Latency_Based_Targeting18[[#This Row],[Improved Time to convert]],2) -> 0 | I348: =Latency_Based_Targeting18[[#This Row],[Time Saved]]/Latency_Based_Targeting18[[#This Row],[Average time to convert in Days]] -> 0

Sheet HighLatencyPairs-Final
A1: Latency Segments | B1: Total Users | C1: Estimated Revenue
A2: High | B2: 53 | C2: 10600
A3: Low | B3: 97 | C3: 4850
A4: Medium | B4: 181 | C4: 18100
A5: Very High | B5: 16 | C5: 4800
A6: Grand Total | B6: 347 | C6: 38350

Sheet WishlistFavs_Data
A1: category_id | B1: total_favorites
A2: 4756105 | B2: 842
A3: 4145813 | B3: 573
A4: 982926 | B4: 473
A5: 2355072 | B5: 463
A6: 2520377 | B6: 373
A7: 4801426 | B7: 372
A8: 3607361 | B8: 350
A9: 2465336 | B9: 295
A10: 3002561 | B10: 266
A11: 1320293 | B11: 264
A12: 4181361 | B12: 204
A13: 149192 | B13: 200
... A601: 3911423 | B601: 3

Sheet WishlistFavs_Assumptions
A1: Conversion Rate | B1: Scenario Label | C1: Total SKUs | D1: Targeted SKUs | E1: Revenue | F1: Conversions | G1: Targeted Favorites
A2: 0.15 | B2: Conservative Estimate | C2: =COUNTA(Table19[category_id]) -> 600 | D2: =0.1*600 -> 60 | E2: =SUM(Table1922[Revenue (Conservative)]) -> 310750 | F2: =SUM(Table1922[Conversions (Conservative)]) -> 1243 | G2: =SUM(Table1922[Total Favorites]) -> 8294
A3: 0.25 | B3: Industry Target | C3: =COUNTA(Table19[category_id]) -> 600 | D3: =0.1*600 -> 60 | E3: =SUM(Table1922[[#All],[Revenue (Benchmark)]]) -> 520250 | F3: =SUM(Table1922[Conversions (Benchmark)]) -> 2081 | G3: =SUM(Table1922[Total Favorites]) -> 8294
A4: 0.3 | B4: Best Case Projection | C4: =COUNTA(Table19[category_id]) -> 600 | D4: =0.1*600 -> 60 | E4: =SUM(Table1922[Revenue (Best Case)]) -> 623250 | F4: =SUM(Table1922[Conversions (Best Case)]) -> 2493 | G4: =SUM(Table1922[Total Favorites]) -> 8294

Sheet WishlistFavs-Simulated Solution
A1: SKU ID | B1: Total Favorites | C1: Avg Order Value | D1: Conversions (Conservative) | E1: Revenue (Conservative) | F1: Conversions (Benchmark) | G1: Revenue (Benchmark) | H1: Conversions (Best Case) | I1: Revenue (Best Case)
A2: 4756105 | B2: 842 | C2: 250 | D2: =ROUND(Table1922[[#This Row],[Total Favorites]]*0.15,0) -> 126 | E2: =Table1922[[#This Row],[Conversions (Conservative)]]*Table1922[[#This Row],[Avg Order Value]] -> 31500 | F2: =ROUND(Table1922[[#This Row],[Total Favorites]]*0.25,0) -> 211 | G2: =Table1922[[#This Row],[Conversions (Benchmark)]]*Table1922[[#This Row],[Avg Order Value]] -> 52750 | H2: =ROUND(Table1922[[#This Row],[Total Favorites]]*0.3,0) -> 253 | I2: =Table1922[[#This Row],[Conversions (Best Case)]]*Table1922[[#This Row],[Avg Order Value]] -> 63250
A3: 4145813 | B3: 573 | C3: 250 | D3: =ROUND(Table1922[[#This Row],[Total Favorites]]*0.15,0) -> 86 | E3: =Table1922[[#This Row],[Conversions (Conservative)]]*Table1922[[#This Row],[Avg Order Value]] -> 21500 | F3: =ROUND(Table1922[[#This Row],[Total Favorites]]*0.25,0) -> 143 | G3: =Table1922[[#This Row],[Conversions (Benchmark)]]*Table1922[[#This Row],[Avg Order Value]] -> 35750 | H3: =ROUND(Table1922[[#This Row],[Total Favorites]]*0.3,0) -> 172 | I3: =Table1922[[#This Row],[Conversions (Best Case)]]*Table1922[[#This Row],[Avg Order Value]] -> 43000
A4: 982926 | B4: 473 | C4: 250 | D4: =ROUND(Table1922[[#This Row],[Total Favorites]]*0.15,0) -> 71 | E4: =Table1922[[#This Row],[Conversions (Conservative)]]*Table1922[[#This Row],[Avg Order Value]] -> 17750 | F4: =ROUND(Table1922[[#This Row],[Total Favorites]]*0.25,0) -> 118 | G4: =Table1922[[#This Row],[Conversions (Benchmark)]]*Table1922[[#This Row],[Avg Order Value]] -> 29500 | H4: =ROUND(Table1922[[#This Row],[Total Favorites]]*0.3,0) -> 142 | I4: =Table1922[[#This Row],[Conversions (Best Case)]]*Table1922[[#This Row],[Avg Order Value]] -> 35500
A5: 2355072 | B5: 463 | C5: 250 | D5: =ROUND(Table1922[[#This Row],[Total Favorites]]*0.15,0) -> 69 | E5: =Table1922[[#This Row],[Conversions (Conservative)]]*Table1922[[#This Row],[Avg Order Value]] -> 17250 | F5: =ROUND(Table1922[[#This Row],[Total Favorites]]*0.25,0) -> 116 | G5: =Table1922[[#This Row],[Conversions (Benchmark)]]*Table1922[[#This Row],[Avg Order Value]] -> 29000 | H5: =ROUND(Table1922[[#This Row],[Total Favorites]]*0.3,0) -> 139 | I5: =Table1922[[#This Row],[Conversions (Best Case)]]*Table1922[[#This Row],[Avg Order Value]] -> 34750
A6: 2520377 | B6: 373 | C6: 250 | D6: =ROUND(Table1922[[#This Row],[Total Favorites]]*0.15,0) -> 56 | E6: =Table1922[[#This Row],[Conversions (Conservative)]]*Table1922[[#This Row],[Avg Order Value]] -> 14000 | F6: =ROUND(Table1922[[#This Row],[Total Favorites]]*0.25,0) -> 93 | G6: =Table1922[[#This Row],[Conversions (Benchmark)]]*Table1922[[#This Row],[Avg Order Value]] -> 23250 | H6: =ROUND(Table1922[[#This Row],[Total Favorites]]*0.3,0) -> 112 | I6: =Table1922[[#This Row],[Conversions (Best Case)]]*Table1922[[#This Row],[Avg Order Value]] -> 28000
A7: 4801426 | B7: 372 | C7: 250 | D7: =ROUND(Table1922[[#This Row],[Total Favorites]]*0.15,0) -> 56 | E7: =Table1922[[#This Row],[Conversions (Conservative)]]*Table1922[[#This Row],[Avg Order Value]] -> 14000 | F7: =ROUND(Table1922[[#This Row],[Total Favorites]]*0.25,0) -> 93 | G7: =Table1922[[#This Row],[Conversions (Benchmark)]]*Table1922[[#This Row],[Avg Order Value]] -> 23250 | H7: =ROUND(Table1922[[#This Row],[Total Favorites]]*0.3,0) -> 112 | I7: =Table1922[[#This Row],[Conversions (Best Case)]]*Table1922[[#This Row],[Avg Order Value]] -> 28000
A8: 3607361 | B8: 350 | C8: 250 | D8: =ROUND(Table1922[[#This Row],[Total Favorites]]*0.15,0) -> 53 | E8: =Table1922[[#This Row],[Conversions (Conservative)]]*Table1922[[#This Row],[Avg Order Value]] -> 13250 | F8: =ROUND(Table1922[[#This Row],[Total Favorites]]*0.25,0) -> 88 | G8: =Table1922[[#This Row],[Conversions (Benchmark)]]*Table1922[[#This Row],[Avg Order Value]] -> 22000 | H8: =ROUND(Table1922[[#This Row],[Total Favorites]]*0.3,0) -> 105 | I8: =Table1922[[#This Row],[Conversions (Best Case)]]*Table1922[[#This Row],[Avg Order Value]] -> 26250
A9: 2465336 | B9: 295 | C9: 250 | D9: =ROUND(Table1922[[#This Row],[Total Favorites]]*0.15,0) -> 44 | E9: =Table1922[[#This Row],[Conversions (Conservative)]]*Table1922[[#This Row],[Avg Order Value]] -> 11000 | F9: =ROUND(Table1922[[#This Row],[Total Favorites]]*0.25,0) -> 74 | G9: =Table1922[[#This Row],[Conversions (Benchmark)]]*Table1922[[#This Row],[Avg Order Value]] -> 18500 | H9: =ROUND(Table1922[[#This Row],[Total Favorites]]*0.3,0) -> 89 | I9: =Table1922[[#This Row],[Conversions (Best Case)]]*Table1922[[#This Row],[Avg Order Value]] -> 22250
A10: 3002561 | B10: 266 | C10: 250 | D10: =ROUND(Table1922[[#This Row],[Total Favorites]]*0.15,0) -> 40 | E10: =Table1922[[#This Row],[Conversions (Conservative)]]*Table1922[[#This Row],[Avg Order Value]] -> 10000 | F10: =ROUND(Table1922[[#This Row],[Total Favorites]]*0.25,0) -> 67 | G10: =Table1922[[#This Row],[Conversions (Benchmark)]]*Table1922[[#This Row],[Avg Order Value]] -> 16750 | H10: =ROUND(Table1922[[#This Row],[Total Favorites]]*0.3,0) -> 80 | I10: =Table1922[[#This Row],[Conversions (Best Case)]]*Table1922[[#This Row],[Avg Order Value]] -> 20000
A11: 1320293 | B11: 264 | C11: 250 | D11: =ROUND(Table1922[[#This Row],[Total Favorites]]*0.15,0) -> 40 | E11: =Table1922[[#This Row],[Conversions (Conservative)]]*Table1922[[#This Row],[Avg Order Value]] -> 10000 | F11: =ROUND(Table1922[[#This Row],[Total Favorites]]*0.25,0) -> 66 | G11: =Table1922[[#This Row],[Conversions (Benchmark)]]*Table1922[[#This Row],[Avg Order Value]] -> 16500 | H11: =ROUND(Table1922[[#This Row],[Total Favorites]]*0.3,0) -> 79 | I11: =Table1922[[#This Row],[Conversions (Best Case)]]*Table1922[[#This Row],[Avg Order Value]] -> 19750
A12: 4181361 | B12: 204 | C12: 250 | D12: =ROUND(Table1922[[#This Row],[Total Favorites]]*0.15,0) -> 31 | E12: =Table1922[[#This Row],[Conversions (Conservative)]]*Table1922[[#This Row],[Avg Order Value]] -> 7750 | F12: =ROUND(Table1922[[#This Row],[Total Favorites]]*0.25,0) -> 51 | G12: =Table1922[[#This Row],[Conversions (Benchmark)]]*Table1922[[#This Row],[Avg Order Value]] -> 12750 | H12: =ROUND(Table1922[[#This Row],[Total Favorites]]*0.3,0) -> 61 | I12: =Table1922[[#This Row],[Conversions (Best Case)]]*Table1922[[#This Row],[Avg Order Value]] -> 15250
A13: 149192 | B13: 200 | C13: 250 | D13: =ROUND(Table1922[[#This Row],[Total Favorites]]*0.15,0) -> 30 | E13: =Table1922[[#This Row],[Conversions (Conservative)]]*Table1922[[#This Row],[Avg Order Value]] -> 7500 | F13: =ROUND(Table1922[[#This Row],[Total Favorites]]*0.25,0) -> 50 | G13: =Table1922[[#This Row],[Conversions (Benchmark)]]*Table1922[[#This Row],[Avg Order Value]] -> 12500 | H13: =ROUND(Table1922[[#This Row],[Total Favorites]]*0.3,0) -> 60 | I13: =Table1922[[#This Row],[Conversions (Best Case)]]*Table1922[[#This Row],[Avg Order Value]] -> 15000
... A61: 285583 | B61: 31 | C61: 250 | D61: =ROUND(Table1922[[#This Row],[Total Favorites]]*0.15,0) -> 5 | E61: =Table1922[[#This Row],[Conversions (Conservative)]]*Table1922[[#This Row],[Avg Order Value]] -> 1250 | F61: =ROUND(Table1922[[#This Row],[Total Favorites]]*0.25,0) -> 8 | G61: =Table1922[[#This Row],[Conversions (Benchmark)]]*Table1922[[#This Row],[Avg Order Value]] -> 2000 | H61: =ROUND(Table1922[[#This Row],[Total Favorites]]*0.3,0) -> 9 | I61: =Table1922[[#This Row],[Conversions (Best Case)]]*Table1922[[#This Row],[Avg Order Value]] -> 2250

Sheet LoyaltyUsers-Data
A1: user_id | B1: total_sessions | C1: total_purchases | D1: last_purchase_time | E1: days_since_last_purchase | F1: loyalty_tier
A2: 655653 | B2: 8 | C2: 2 | D2: 43069.478 | E2: 3 | F2: Gold
A3: 984143 | B3: 7 | C3: 1 | D3: 43069.227 | E3: 3 | F3: Gold
A4: 503596 | B4: 7 | C4: 2 | D4: 43066.211 | E4: 6 | F4: Gold
A5: 103648 | B5: 7 | C5: 1 | D5: 43066.336 | E5: 6 | F5: Gold
A6: 479506 | B6: 7 | C6: 1 | D6: 43069.55 | E6: 3 | F6: Gold
A7: 876546 | B7: 7 | C7: 1 | D7: 43067.606 | E7: 5 | F7: Gold
A8: 466909 | B8: 7 | C8: 1 | D8: 43068.169 | E8: 4 | F8: Gold
A9: 896538 | B9: 7 | C9: 1 | D9: 43064.678 | E9: 8 | F9: Gold
A10: 273220 | B10: 7 | C10: 1 | D10: 43067.483 | E10: 5 | F10: Gold
A11: 369810 | B11: 6 | C11: 1 | D11: 43068.179 | E11: 4 | F11: Gold
A12: 556875 | B12: 6 | C12: 2 | D12: 43067.382 | E12: 5 | F12: Gold
A13: 302575 | B13: 6 | C13: 1 | D13: 43064.698 | E13: 8 | F13: Gold
... A1902: 265631 | B1902: 2 | C1902: 1 | D1902: 43068.525 | E1902: 4 | F1902: Silver

Sheet LoyaltyUsers-Simulated Sol
A1: Conversion Rate | B1: Scenario | C1: Currently Loyal Users | D1: Total Users | E1: Loyalty Rate | F1: Campaign Pool Size | G1: Target Loyal Users | H1: Expected New Loyal Users | I1: Loyal Users after Campaign | J1: Avg Revenue/User | K1: Projected Revenue Gain | L1: Post Campaign Loyalty | M1: Percentage Upliftment In Loyalty
A2: 0.15 | B2: Conservative Estimate | C2: =COUNTIFS('LoyaltyUsers-Data'!B:B,">=2",'LoyaltyUsers-Data'!C:C,">=2") -> 205 | D2: 242386 | E2: =C2/D2 -> 0.00084575842 | F2: =COUNT('LoyaltyUsers-Data'!A:A) -> 1901 | G2: =ROUND(0.01*D2,0) -> 2424 | H2: =ROUND(A2*F2,0) -> 285 | I2: =Table23[[#This Row],[Expected New Loyal Users]]+Table23[[#This Row],[Currently Loyal Users]] -> 490 | J2: 250 | K2: =H2*J2 -> 71250 | L2: =('LoyaltyUsers-Simulated Sol'!$H2+'LoyaltyUsers-Simulated Sol'!$C2)/'LoyaltyUsers-Simulated Sol'!$D2 -> 0.0020215689 | M2: =('LoyaltyUsers-Simulated Sol'!$L2-'LoyaltyUsers-Simulated Sol'!$E2)/'LoyaltyUsers-Simulated Sol'!$E2 -> 1.3902439
A3: 0.25 | B3: Industry Target | C3: =COUNTIFS('LoyaltyUsers-Data'!B:B,">=2",'LoyaltyUsers-Data'!C:C,">=2") -> 205 | D3: 242386 | E3: =C3/D3 -> 0.00084575842 | F3: =COUNT('LoyaltyUsers-Data'!A:A) -> 1901 | G3: =ROUND(0.01*D3,0) -> 2424 | H3: =ROUND(A3*F3,0) -> 475 | I3: =Table23[[#This Row],[Expected New Loyal Users]]+Table23[[#This Row],[Currently Loyal Users]] -> 680 | J3: 250 | K3: =H3*J3 -> 118750 | L3: =('LoyaltyUsers-Simulated Sol'!$H3+'LoyaltyUsers-Simulated Sol'!$C3)/'LoyaltyUsers-Simulated Sol'!$D3 -> 0.0028054426 | M3: =('LoyaltyUsers-Simulated Sol'!$L3-'LoyaltyUsers-Simulated Sol'!$E3)/'LoyaltyUsers-Simulated Sol'!$E3 -> 2.3170732
A4: 0.3 | B4: Best Case Projection | C4: =COUNTIFS('LoyaltyUsers-Data'!B:B,">=2",'LoyaltyUsers-Data'!C:C,">=2") -> 205 | D4: 242386 | E4: =C4/D4 -> 0.00084575842 | F4: =COUNT('LoyaltyUsers-Data'!A:A) -> 1901 | G4: =ROUND(0.01*D4,0) -> 2424 | H4: =ROUND(A4*F4,0) -> 570 | I4: =Table23[[#This Row],[Expected New Loyal Users]]+Table23[[#This Row],[Currently Loyal Users]] -> 775 | J4: 250 | K4: =H4*J4 -> 142500 | L4: =('LoyaltyUsers-Simulated Sol'!$H4+'LoyaltyUsers-Simulated Sol'!$C4)/'LoyaltyUsers-Simulated Sol'!$D4 -> 0.0031973794 | M4: =('LoyaltyUsers-Simulated Sol'!$L4-'LoyaltyUsers-Simulated Sol'!$E4)/'LoyaltyUsers-Simulated Sol'!$E4 -> 2.7804878
E11: Loyalty base grows by 185% post-campaign (from 205 → 585 users). Uplifted loyalty rate from 0.08% to 0.24%. While not reaching 1%, it's a meaningful recovery boost toward long-term loyalty goals. Revenue lift of ₹95,000 justifies targeted CRM campaigns.

Sheet HourlyBehavior-Data
A1: hour_of_day | B1: total_actions | C1: views | D1: carted | E1: converted
A2: 14 | B2: 47848 | C2: 42986 | D2: 2783 | E2: 719
A3: 13 | B3: 46821 | C3: 42412 | D3: 2529 | E3: 705
A4: 12 | B4: 39645 | C4: 35945 | D4: 2113 | E4: 603
A5: 15 | B5: 37114 | C5: 33160 | D5: 2297 | E5: 529
A6: 8 | B6: 24817 | C6: 22371 | D6: 1271 | E6: 467
A7: 11 | B7: 30391 | C7: 27687 | D7: 1473 | E7: 466
A8: 5 | B8: 24016 | C8: 21606 | D8: 1282 | E8: 461
A9: 7 | B9: 25745 | C9: 23303 | D9: 1361 | E9: 459
A10: 3 | B10: 21784 | C10: 19444 | D10: 1228 | E10: 457
A11: 6 | B11: 24783 | C11: 22328 | D11: 1323 | E11: 444
A12: 4 | B12: 21102 | C12: 18902 | D12: 1129 | E12: 431
A13: 2 | B13: 22683 | C13: 20351 | D13: 1222 | E13: 418
... A25: 21 | B25: 2990 | C25: 2717 | D25: 180 | E25: 29

Sheet HourlyBehavior-Simulated_Sol
A1: hour_of_day | B1: total_actions | C1: views | D1: carted | E1: converted | F1: Conversion Rate | G1: Avg Revenue/User | H1: Campaign Cost per 1000 views | I1: Revenue per1000 views | J1: Total Campaign Cost | K1: Total Revenue | L1: ROI Calculation
A2: 0 | B2: 15296 | C2: 13754 | D2: 844 | E2: 248 | F2: =ROUND(Time_Sensitive_Engagement_By_Hour27[[#This Row],[converted]]/Time_Sensitive_Engagement_By_Hour27[[#This Row],[views]],5) -> 0.01803 | G2: 250 | H2: 120 | I2: =Time_Sensitive_Engagement_By_Hour27[[#This Row],[Avg Revenue/User]]*Time_Sensitive_Engagement_By_Hour27[[#This Row],[Conversion Rate]]*1000 -> 4507.5 | J2: =(Time_Sensitive_Engagement_By_Hour27[[#This Row],[Campaign Cost per 1000 views]]*Time_Sensitive_Engagement_By_Hour27[[#This Row],[views]])/1000 -> 1650.48 | K2: =Time_Sensitive_Engagement_By_Hour27[[#This Row],[Avg Revenue/User]]*Time_Sensitive_Engagement_By_Hour27[[#This Row],[converted]] -> 62000 | L2: =Time_Sensitive_Engagement_By_Hour27[[#This Row],[Total Revenue]]-Time_Sensitive_Engagement_By_Hour27[[#This Row],[Total Campaign Cost]] -> 60349.52
A3: 1 | B3: 18795 | C3: 16926 | D3: 960 | E3: 342 | F3: =ROUND(Time_Sensitive_Engagement_By_Hour27[[#This Row],[converted]]/Time_Sensitive_Engagement_By_Hour27[[#This Row],[views]],5) -> 0.02021 | G3: 250 | H3: 120 | I3: =Time_Sensitive_Engagement_By_Hour27[[#This Row],[Avg Revenue/User]]*Time_Sensitive_Engagement_By_Hour27[[#This Row],[Conversion Rate]]*1000 -> 5052.5 | J3: =(Time_Sensitive_Engagement_By_Hour27[[#This Row],[Campaign Cost per 1000 views]]*Time_Sensitive_Engagement_By_Hour27[[#This Row],[views]])/1000 -> 2031.12 | K3: =Time_Sensitive_Engagement_By_Hour27[[#This Row],[Avg Revenue/User]]*Time_Sensitive_Engagement_By_Hour27[[#This Row],[converted]] -> 85500 | L3: =Time_Sensitive_Engagement_By_Hour27[[#This Row],[Total Revenue]]-Time_Sensitive_Engagement_By_Hour27[[#This Row],[Total Campaign Cost]] -> 83468.88
A4: 2 | B4: 22683 | C4: 20351 | D4: 1222 | E4: 418 | F4: =ROUND(Time_Sensitive_Engagement_By_Hour27[[#This Row],[converted]]/Time_Sensitive_Engagement_By_Hour27[[#This Row],[views]],5) -> 0.02054 | G4: 250 | H4: 120 | I4: =Time_Sensitive_Engagement_By_Hour27[[#This Row],[Avg Revenue/User]]*Time_Sensitive_Engagement_By_Hour27[[#This Row],[Conversion Rate]]*1000 -> 5135 | J4: =(Time_Sensitive_Engagement_By_Hour27[[#This Row],[Campaign Cost per 1000 views]]*Time_Sensitive_Engagement_By_Hour27[[#This Row],[views]])/1000 -> 2442.12 | K4: =Time_Sensitive_Engagement_By_Hour27[[#This Row],[Avg Revenue/User]]*Time_Sensitive_Engagement_By_Hour27[[#This Row],[converted]] -> 104500 | L4: =Time_Sensitive_Engagement_By_Hour27[[#This Row],[Total Revenue]]-Time_Sensitive_Engagement_By_Hour27[[#This Row],[Total Campaign Cost]] -> 102057.88
A5: 3 | B5: 21784 | C5: 19444 | D5: 1228 | E5: 457 | F5: =ROUND(Time_Sensitive_Engagement_By_Hour27[[#This Row],[converted]]/Time_Sensitive_Engagement_By_Hour27[[#This Row],[views]],5) -> 0.0235 | G5: 250 | H5: 120 | I5: =Time_Sensitive_Engagement_By_Hour27[[#This Row],[Avg Revenue/User]]*Time_Sensitive_Engagement_By_Hour27[[#This Row],[Conversion Rate]]*1000 -> 5875 | J5: =(Time_Sensitive_Engagement_By_Hour27[[#This Row],[Campaign Cost per 1000 views]]*Time_Sensitive_Engagement_By_Hour27[[#This Row],[views]])/1000 -> 2333.28 | K5: =Time_Sensitive_Engagement_By_Hour27[[#This Row],[Avg Revenue/User]]*Time_Sensitive_Engagement_By_Hour27[[#This Row],[converted]] -> 114250 | L5: =Time_Sensitive_Engagement_By_Hour27[[#This Row],[Total Revenue]]-Time_Sensitive_Engagement_By_Hour27[[#This Row],[Total Campaign Cost]] -> 111916.72
A6: 4 | B6: 21102 | C6: 18902 | D6: 1129 | E6: 431 | F6: =ROUND(Time_Sensitive_Engagement_By_Hour27[[#This Row],[converted]]/Time_Sensitive_Engagement_By_Hour27[[#This Row],[views]],5) -> 0.0228 | G6: 250 | H6: 120 | I6: =Time_Sensitive_Engagement_By_Hour27[[#This Row],[Avg Revenue/User]]*Time_Sensitive_Engagement_By_Hour27[[#This Row],[Conversion Rate]]*1000 -> 5700 | J6: =(Time_Sensitive_Engagement_By_Hour27[[#This Row],[Campaign Cost per 1000 views]]*Time_Sensitive_Engagement_By_Hour27[[#This Row],[views]])/1000 -> 2268.24 | K6: =Time_Sensitive_Engagement_By_Hour27[[#This Row],[Avg Revenue/User]]*Time_Sensitive_Engagement_By_Hour27[[#This Row],[converted]] -> 107750 | L6: =Time_Sensitive_Engagement_By_Hour27[[#This Row],[Total Revenue]]-Time_Sensitive_Engagement_By_Hour27[[#This Row],[Total Campaign Cost]] -> 105481.76
A7: 5 | B7: 24016 | C7: 21606 | D7: 1282 | E7: 461 | F7: =ROUND(Time_Sensitive_Engagement_By_Hour27[[#This Row],[converted]]/Time_Sensitive_Engagement_By_Hour27[[#This Row],[views]],5) -> 0.02134 | G7: 250 | H7: 120 | I7: =Time_Sensitive_Engagement_By_Hour27[[#This Row],[Avg Revenue/User]]*Time_Sensitive_Engagement_By_Hour27[[#This Row],[Conversion Rate]]*1000 -> 5335 | J7: =(Time_Sensitive_Engagement_By_Hour27[[#This Row],[Campaign Cost per 1000 views]]*Time_Sensitive_Engagement_By_Hour27[[#This Row],[views]])/1000 -> 2592.72 | K7: =Time_Sensitive_Engagement_By_Hour27[[#This Row],[Avg Revenue/User]]*Time_Sensitive_Engagement_By_Hour27[[#This Row],[converted]] -> 115250 | L7: =Time_Sensitive_Engagement_By_Hour27[[#This Row],[Total Revenue]]-Time_Sensitive_Engagement_By_Hour27[[#This Row],[Total Campaign Cost]] -> 112657.28
A8: 6 | B8: 24783 | C8: 22328 | D8: 1323 | E8: 444 | F8: =ROUND(Time_Sensitive_Engagement_By_Hour27[[#This Row],[converted]]/Time_Sensitive_Engagement_By_Hour27[[#This Row],[views]],5) -> 0.01989 | G8: 250 | H8: 120 | I8: =Time_Sensitive_Engagement_By_Hour27[[#This Row],[Avg Revenue/User]]*Time_Sensitive_Engagement_By_Hour27[[#This Row],[Conversion Rate]]*1000 -> 4972.5 | J8: =(Time_Sensitive_Engagement_By_Hour27[[#This Row],[Campaign Cost per 1000 views]]*Time_Sensitive_Engagement_By_Hour27[[#This Row],[views]])/1000 -> 2679.36 | K8: =Time_Sensitive_Engagement_By_Hour27[[#This Row],[Avg Revenue/User]]*Time_Sensitive_Engagement_By_Hour27[[#This Row],[converted]] -> 111000 | L8: =Time_Sensitive_Engagement_By_Hour27[[#This Row],[Total Revenue]]-Time_Sensitive_Engagement_By_Hour27[[#This Row],[Total Campaign Cost]] -> 108320.64
A9: 7 | B9: 25745 | C9: 23303 | D9: 1361 | E9: 459 | F9: =ROUND(Time_Sensitive_Engagement_By_Hour27[[#This Row],[converted]]/Time_Sensitive_Engagement_By_Hour27[[#This Row],[views]],5) -> 0.0197 | G9: 250 | H9: 120 | I9: =Time_Sensitive_Engagement_By_Hour27[[#This Row],[Avg Revenue/User]]*Time_Sensitive_Engagement_By_Hour27[[#This Row],[Conversion Rate]]*1000 -> 4925 | J9: =(Time_Sensitive_Engagement_By_Hour27[[#This Row],[Campaign Cost per 1000 views]]*Time_Sensitive_Engagement_By_Hour27[[#This Row],[views]])/1000 -> 2796.36 | K9: =Time_Sensitive_Engagement_By_Hour27[[#This Row],[Avg Revenue/User]]*Time_Sensitive_Engagement_By_Hour27[[#This Row],[converted]] -> 114750 | L9: =Time_Sensitive_Engagement_By_Hour27[[#This Row],[Total Revenue]]-Time_Sensitive_Engagement_By_Hour27[[#This Row],[Total Campaign Cost]] -> 111953.64
A10: 8 | B10: 24817 | C10: 22371 | D10: 1271 | E10: 467 | F10: =ROUND(Time_Sensitive_Engagement_By_Hour27[[#This Row],[converted]]/Time_Sensitive_Engagement_By_Hour27[[#This Row],[views]],5) -> 0.02088 | G10: 250 | H10: 120 | I10: =Time_Sensitive_Engagement_By_Hour27[[#This Row],[Avg Revenue/User]]*Time_Sensitive_Engagement_By_Hour27[[#This Row],[Conversion Rate]]*1000 -> 5220 | J10: =(Time_Sensitive_Engagement_By_Hour27[[#This Row],[Campaign Cost per 1000 views]]*Time_Sensitive_Engagement_By_Hour27[[#This Row],[views]])/1000 -> 2684.52 | K10: =Time_Sensitive_Engagement_By_Hour27[[#This Row],[Avg Revenue/User]]*Time_Sensitive_Engagement_By_Hour27[[#This Row],[converted]] -> 116750 | L10: =Time_Sensitive_Engagement_By_Hour27[[#This Row],[Total Revenue]]-Time_Sensitive_Engagement_By_Hour27[[#This Row],[Total Campaign Cost]] -> 114065.48
A11: 9 | B11: 21826 | C11: 19725 | D11: 1150 | E11: 355 | F11: =ROUND(Time_Sensitive_Engagement_By_Hour27[[#This Row],[converted]]/Time_Sensitive_Engagement_By_Hour27[[#This Row],[views]],5) -> 0.018 | G11: 250 | H11: 120 | I11: =Time_Sensitive_Engagement_By_Hour27[[#This Row],[Avg Revenue/User]]*Time_Sensitive_Engagement_By_Hour27[[#This Row],[Conversion Rate]]*1000 -> 4500 | J11: =(Time_Sensitive_Engagement_By_Hour27[[#This Row],[Campaign Cost per 1000 views]]*Time_Sensitive_Engagement_By_Hour27[[#This Row],[views]])/1000 -> 2367 | K11: =Time_Sensitive_Engagement_By_Hour27[[#This Row],[Avg Revenue/User]]*Time_Sensitive_Engagement_By_Hour27[[#This Row],[converted]] -> 88750 | L11: =Time_Sensitive_Engagement_By_Hour27[[#This Row],[Total Revenue]]-Time_Sensitive_Engagement_By_Hour27[[#This Row],[Total Campaign Cost]] -> 86383
A12: 10 | B12: 22755 | C12: 20657 | D12: 1123 | E12: 366 | F12: =ROUND(Time_Sensitive_Engagement_By_Hour27[[#This Row],[converted]]/Time_Sensitive_Engagement_By_Hour27[[#This Row],[views]],5) -> 0.01772 | G12: 250 | H12: 120 | I12: =Time_Sensitive_Engagement_By_Hour27[[#This Row],[Avg Revenue/User]]*Time_Sensitive_Engagement_By_Hour27[[#This Row],[Conversion Rate]]*1000 -> 4430 | J12: =(Time_Sensitive_Engagement_By_Hour27[[#This Row],[Campaign Cost per 1000 views]]*Time_Sensitive_Engagement_By_Hour27[[#This Row],[views]])/1000 -> 2478.84 | K12: =Time_Sensitive_Engagement_By_Hour27[[#This Row],[Avg Revenue/User]]*Time_Sensitive_Engagement_By_Hour27[[#This Row],[converted]] -> 91500 | L12: =Time_Sensitive_Engagement_By_Hour27[[#This Row],[Total Revenue]]-Time_Sensitive_Engagement_By_Hour27[[#This Row],[Total Campaign Cost]] -> 89021.16
A13: 11 | B13: 30391 | C13: 27687 | D13: 1473 | E13: 466 | F13: =ROUND(Time_Sensitive_Engagement_By_Hour27[[#This Row],[converted]]/Time_Sensitive_Engagement_By_Hour27[[#This Row],[views]],5) -> 0.01683 | G13: 250 | H13: 120 | I13: =Time_Sensitive_Engagement_By_Hour27[[#This Row],[Avg Revenue/User]]*Time_Sensitive_Engagement_By_Hour27[[#This Row],[Conversion Rate]]*1000 -> 4207.5 | J13: =(Time_Sensitive_Engagement_By_Hour27[[#This Row],[Campaign Cost per 1000 views]]*Time_Sensitive_Engagement_By_Hour27[[#This Row],[views]])/1000 -> 3322.44 | K13: =Time_Sensitive_Engagement_By_Hour27[[#This Row],[Avg Revenue/User]]*Time_Sensitive_Engagement_By_Hour27[[#This Row],[converted]] -> 116500 | L13: =Time_Sensitive_Engagement_By_Hour27[[#This Row],[Total Revenue]]-Time_Sensitive_Engagement_By_Hour27[[#This Row],[Total Campaign Cost]] -> 113177.56
... A25: 23 | B25: 9470 | C25: 8498 | D25: 562 | E25: 113 | F25: =ROUND(Time_Sensitive_Engagement_By_Hour27[[#This Row],[converted]]/Time_Sensitive_Engagement_By_Hour27[[#This Row],[views]],5) -> 0.0133 | G25: 250 | H25: 120 | I25: =Time_Sensitive_Engagement_By_Hour27[[#This Row],[Avg Revenue/User]]*Time_Sensitive_Engagement_By_Hour27[[#This Row],[Conversion Rate]]*1000 -> 3325 | J25: =(Time_Sensitive_Engagement_By_Hour27[[#This Row],[Campaign Cost per 1000 views]]*Time_Sensitive_Engagement_By_Hour27[[#This Row],[views]])/1000 -> 1019.76 | K25: =Time_Sensitive_Engagement_By_Hour27[[#This Row],[Avg Revenue/User]]*Time_Sensitive_Engagement_By_Hour27[[#This Row],[converted]] -> 28250 | L25: =Time_Sensitive_Engagement_By_Hour27[[#This Row],[Total Revenue]]-Time_Sensitive_Engagement_By_Hour27[[#This Row],[Total Campaign Cost]] -> 27230.24
A27: Campaign ROI Summary by Hour | F27: Top Hourly Windows for Campaign Launch
B31: Metric | C31: Value/Insight | F31: Hour Range | G31: Campaign Window | H31: ROI Class | I31: Action
B32: Peak ROI Slot | C32: 3 AM – 5 AM (ROI > ₹5,200/1000 views) | F32: 3–5 | G32: Early Morning Peak | H32: Ultra-High ROI | I32: Strong candidate – Send offers
B33: High ROI Tier | C33: Hours 1–8 (ROI consistently > ₹4,800) | F33: 6–9 | G33: Morning Activation | H33: High ROI | I33: Ideal for retargeting
B34: Break-even Threshold | C34: ~₹120 campaign cost/1000 views | F34: 12–17 | G34: Midday Window | H34: Moderate ROI | I34: Use only for loyalty nudges
B35: Low ROI Hours | C35: 18–23 (ROI < ₹3,300) – Avoid campaigns | F35: 18–23 | G35: Evening Drift | H35: Low ROI | I35: Avoid costly impressions
B40: Strategic Decision
B43: Restrict major paid campaigns to 3–9 AM, targeting users active during these hours.
B44: These slots deliver 2x–3x higher ROI than afternoon/evening hours.
B45: Campaigns during late evenings and night (post 6 PM) should be deprioritized unless segment-specific targeting (e.g., Night Owls) shows high responsiveness.
